README.rst
VERSION
requirements.txt
vcfminerclient/__init__.py
vcfminerclient-0.1.1.dist-info/DESCRIPTION.rst
vcfminerclient-0.1.1.dist-info/METADATA
vcfminerclient-0.1.1.dist-info/RECORD
vcfminerclient-0.1.1.dist-info/WHEEL
vcfminerclient-0.1.1.dist-info/metadata.json
vcfminerclient-0.1.1.dist-info/top_level.txt
vcfminerclient-0.1.1.dist-info/zip-safe
