Metadata-Version: 2.0
Name: vcfminerclient
Version: 0.1.1
Summary: client package for VCFMiner
Home-page: https://github.com/ratzeni/vcf-miner.client
Author: Atzeni Rossano
Author-email: <ratzeni@crs4.it>
License: MIT
Keywords: utilities
Platform: Posix; MacOS X; Windows
Classifier: Development Status :: 3 - Alpha
Classifier: Intended Audience :: Developers
Classifier: License :: OSI Approved :: MIT License
Classifier: Operating System :: OS Independent
Classifier: Topic :: Internet
Classifier: Programming Language :: Python :: 2.7
Classifier: Programming Language :: Python :: 3.5
